localdex/__init__.py
localdex/cli.py
localdex/core.py
localdex/data_loader.py
localdex/download_data.py
localdex/exceptions.py
localdex/random_battles.py
localdex/models/__init__.py
localdex/models/ability.py
localdex/models/item.py
localdex/models/move.py
localdex/models/pokemon.py
localdex-0.2.1.dist-info/METADATA
localdex-0.2.1.dist-info/WHEEL
localdex-0.2.1.dist-info/entry_points.txt
localdex-0.2.1.dist-info/top_level.txt
localdex-0.2.1.dist-info/RECORD
