Metadata-Version: 2.4
Name: localdex
Version: 0.2.1
Summary: A local Pokemon data repository/Pokedex with fast offline access
Author-email: LocalDex Team <localdex@example.com>
License: MIT
Project-URL: Homepage, https://github.com/colefoster/localdex
Project-URL: Documentation, https://localdex.readthedocs.io/
Project-URL: Repository, https://github.com/colefoster/localdex
Project-URL: Bug Tracker, https://github.com/colefoster/localdex/issues
Classifier: Development Status :: 3 - Alpha
Classifier: Intended Audience :: Developers
Classifier: Programming Language :: Python :: 3
Classifier: Programming Language :: Python :: 3.8
Classifier: Programming Language :: Python :: 3.9
Classifier: Programming Language :: Python :: 3.10
Classifier: Programming Language :: Python :: 3.11
Classifier: Programming Language :: Python :: 3.12
Classifier: Topic :: Games/Entertainment
Classifier: Topic :: Software Development :: Libraries :: Python Modules
Requires-Python: >=3.8
Requires-Dist: requests
Requires-Dist: typing-extensions
Provides-Extra: core
Provides-Extra: gen1
Provides-Extra: gen2
Provides-Extra: gen3
Provides-Extra: gen4
Provides-Extra: gen5
Provides-Extra: gen6
Provides-Extra: gen7
Provides-Extra: gen8
Provides-Extra: gen9
Provides-Extra: sprites
Provides-Extra: competitive
Provides-Extra: learnsets
Provides-Extra: items
Provides-Extra: abilities
Provides-Extra: full
Requires-Dist: localdex[abilities,competitive,gen1,gen2,gen3,gen4,gen5,gen6,gen7,gen8,gen9,items,learnsets,sprites]; extra == "full"
Provides-Extra: dev
Requires-Dist: pytest>=7.0.0; extra == "dev"
Requires-Dist: pytest-cov>=4.0.0; extra == "dev"
Requires-Dist: black>=22.0.0; extra == "dev"
Requires-Dist: isort>=5.0.0; extra == "dev"
Requires-Dist: mypy>=1.0.0; extra == "dev"
Requires-Dist: flake8>=5.0.0; extra == "dev"
